arpa2.quickder-1.4.0-py3.7-nspkg.pth
PYTHON.MD
_quickder.cpython-37m-x86_64-linux-gnu.so
arpa2.quickder-1.4.0.dist-info/WHEEL
arpa2.quickder-1.4.0.dist-info/RECORD
arpa2.quickder-1.4.0.dist-info/top_level.txt
arpa2.quickder-1.4.0.dist-info/METADATA
arpa2.quickder-1.4.0.dist-info/LICENSE.MD
arpa2.quickder-1.4.0.dist-info/namespace_packages.txt
arpa2/quickder/__init__.py
arpa2/quickder/api.py
arpa2/quickder/builder.py
arpa2/quickder/primitive.py
arpa2/quickder/packstx.py
arpa2/quickder/classes.py
arpa2/quickder/format.py
