Metadata-Version: 2.1
Name: arpa2.quickder
Version: 1.4.0
Summary: Quick DER -- Abstract Base Classes for generated ASN.1 handlers
Home-page: https://gitlab.com/arpa2/quick-der
Author: Rick van Rein (for the ARPA2 Quick DER project)
Author-email: rick@openfortress.nl
License: UNKNOWN
Platform: UNKNOWN
Provides-Extra: TOOLS
